{
	"$schema": "http://schema.management.azure.com/schemas/2015-01-01/deploymentTemplate.json#",
	"contentVersion": "1.0.0.0",
	"parameters": {
		"factoryName": {
			"type": "string",
			"metadata": "Data Factory name",
			"defaultValue": "MateiDF"
		},
		"AzureBlobStorage1_connectionString": {
			"type": "secureString",
			"metadata": "Secure string for 'connectionString' of 'AzureBlobStorage1'"
		},
		"AzureSqlDatabase1_connectionString": {
			"type": "secureString",
			"metadata": "Secure string for 'connectionString' of 'AzureSqlDatabase1'"
		},
		"MySql1_connectionString": {
			"type": "secureString",
			"metadata": "Secure string for 'connectionString' of 'MySql1'"
		},
		"AzureKeyVault1_properties_typeProperties_baseUrl": {
			"type": "string",
			"defaultValue": "https://MateiKeys.vault.azure.net/"
		},
		"TumblingWindow1_properties_pipeline_parameters_param1": {
			"type": "string",
			"defaultValue": "@trigger().outputs.windowStartTime"
		}
	},
	"variables": {
		"factoryId": "[concat('Microsoft.DataFactory/factories/', parameters('factoryName'))]"
	},
	"resources": [
		{
			"name": "[concat(parameters('factoryName'), '/BlobToBlob')]",
			"type": "Microsoft.DataFactory/factories/pipelines",
			"apiVersion": "2018-06-01",
			"properties": {
				"activities": [
					{
						"name": "CopyBlobToBlob1",
						"type": "Copy",
						"dependsOn": [],
						"policy": {
							"timeout": "7.00:00:00",
							"retry": 0,
							"retryIntervalInSeconds": 30,
							"secureOutput": false,
							"secureInput": false
						},
						"userProperties": [],
						"typeProperties": {
							"source": {
								"type": "DelimitedTextSource",
								"storeSettings": {
									"type": "AzureBlobStorageReadSettings",
									"recursive": true,
									"enablePartitionDiscovery": false
								},
								"formatSettings": {
									"type": "DelimitedTextReadSettings"
								}
							},
							"sink": {
								"type": "DelimitedTextSink",
								"storeSettings": {
									"type": "AzureBlobStorageWriteSettings"
								},
								"formatSettings": {
									"type": "DelimitedTextWriteSettings",
									"quoteAllText": true,
									"fileExtension": ".txt"
								}
							},
							"enableStaging": false,
							"translator": {
								"type": "TabularTranslator",
								"typeConversion": true,
								"typeConversionSettings": {
									"allowDataTruncation": true,
									"treatBooleanAsNumber": false
								}
							}
						},
						"inputs": [
							{
								"referenceName": "People1",
								"type": "DatasetReference",
								"parameters": {}
							}
						],
						"outputs": [
							{
								"referenceName": "Output1",
								"type": "DatasetReference",
								"parameters": {}
							}
						]
					}
				],
				"policy": {
					"elapsedTimeMetric": {},
					"cancelAfter": {}
				},
				"annotations": []
			},
			"dependsOn": [
				"[concat(variables('factoryId'), '/datasets/People1')]",
				"[concat(variables('factoryId'), '/datasets/Output1')]"
			]
		},
		{
			"name": "[concat(parameters('factoryName'), '/Connectors')]",
			"type": "Microsoft.DataFactory/factories/pipelines",
			"apiVersion": "2018-06-01",
			"properties": {
				"activities": [
					{
						"name": "BlobToSql",
						"type": "Copy",
						"dependsOn": [],
						"policy": {
							"timeout": "7.00:00:00",
							"retry": 3,
							"retryIntervalInSeconds": 30,
							"secureOutput": false,
							"secureInput": false
						},
						"userProperties": [],
						"typeProperties": {
							"source": {
								"type": "DelimitedTextSource",
								"storeSettings": {
									"type": "AzureBlobStorageReadSettings",
									"recursive": true,
									"enablePartitionDiscovery": false
								},
								"formatSettings": {
									"type": "DelimitedTextReadSettings"
								}
							},
							"sink": {
								"type": "AzureSqlSink",
								"writeBehavior": "insert",
								"sqlWriterUseTableLock": false
							},
							"enableStaging": false,
							"translator": {
								"type": "TabularTranslator",
								"mappings": [
									{
										"source": {
											"name": "Age",
											"type": "String",
											"physicalType": "String"
										},
										"sink": {
											"name": "Age",
											"type": "Int32",
											"physicalType": "int"
										}
									},
									{
										"source": {
											"name": "FirstName",
											"type": "String",
											"physicalType": "String"
										},
										"sink": {
											"name": "FirstName",
											"type": "String",
											"physicalType": "nvarchar"
										}
									},
									{
										"source": {
											"name": "LastName",
											"type": "String",
											"physicalType": "String"
										},
										"sink": {
											"name": "LastName",
											"type": "String",
											"physicalType": "nvarchar"
										}
									}
								],
								"typeConversion": true,
								"typeConversionSettings": {
									"allowDataTruncation": true,
									"treatBooleanAsNumber": false
								}
							}
						},
						"inputs": [
							{
								"referenceName": "People1",
								"type": "DatasetReference",
								"parameters": {}
							}
						],
						"outputs": [
							{
								"referenceName": "AzureSqlPeople",
								"type": "DatasetReference",
								"parameters": {}
							}
						]
					}
				],
				"policy": {
					"elapsedTimeMetric": {},
					"cancelAfter": {}
				},
				"annotations": []
			},
			"dependsOn": [
				"[concat(variables('factoryId'), '/datasets/People1')]",
				"[concat(variables('factoryId'), '/datasets/AzureSqlPeople')]"
			]
		},
		{
			"name": "[concat(parameters('factoryName'), '/CopyFilesfromMultipleContainers')]",
			"type": "Microsoft.DataFactory/factories/pipelines",
			"apiVersion": "2018-06-01",
			"properties": {
				"description": "Scan the file path on your source storage store and get the container list.",
				"activities": [
					{
						"name": "EnumerateContainersList",
						"type": "GetMetadata",
						"dependsOn": [],
						"policy": {
							"timeout": "7.00:00:00",
							"retry": 0,
							"retryIntervalInSeconds": 30,
							"secureOutput": false,
							"secureInput": false
						},
						"userProperties": [],
						"typeProperties": {
							"dataset": {
								"referenceName": "BinarySourceFileStore",
								"type": "DatasetReference",
								"parameters": {
									"container": {
										"value": "@pipeline().parameters.SourceFileFolder",
										"type": "Expression"
									},
									"directory": {
										"value": "@pipeline().parameters.SourceFileDirectory",
										"type": "Expression"
									}
								}
							},
							"fieldList": [
								"childItems"
							],
							"storeSettings": {
								"type": "AzureBlobStorageReadSettings",
								"recursive": true
							}
						}
					},
					{
						"name": "ForEachContainer",
						"description": "Get the container list from Metadata activity and then iterates each of them to Copy activity.",
						"type": "ForEach",
						"dependsOn": [
							{
								"activity": "EnumerateContainersList",
								"dependencyConditions": [
									"Succeeded"
								]
							}
						],
						"userProperties": [],
						"typeProperties": {
							"items": {
								"value": "@activity('EnumerateContainersList').output.childItems",
								"type": "Expression"
							},
							"batchCount": 4,
							"activities": [
								{
									"name": "CopyOneContainer",
									"description": "Copy each container from source storage store to destination store.",
									"type": "Copy",
									"dependsOn": [],
									"policy": {
										"timeout": "7.00:00:00",
										"retry": 0,
										"retryIntervalInSeconds": 30,
										"secureOutput": false,
										"secureInput": false
									},
									"userProperties": [],
									"typeProperties": {
										"source": {
											"type": "BinarySource",
											"storeSettings": {
												"type": "AzureBlobStorageReadSettings",
												"recursive": true
											}
										},
										"sink": {
											"type": "BinarySink",
											"storeSettings": {
												"type": "AzureBlobStorageWriteSettings",
												"copyBehavior": "PreserveHierarchy"
											}
										},
										"enableStaging": false
									},
									"inputs": [
										{
											"referenceName": "BinarySourceFileStore",
											"type": "DatasetReference",
											"parameters": {
												"container": {
													"value": "@pipeline().parameters.SourceFileFolder",
													"type": "Expression"
												},
												"directory": {
													"value": "@concat(pipeline().parameters.SourceFileDirectory,'/',item().name)",
													"type": "Expression"
												}
											}
										}
									],
									"outputs": [
										{
											"referenceName": "BinarySinkFileStore",
											"type": "DatasetReference",
											"parameters": {
												"container": {
													"value": "@pipeline().parameters.DestinationFileFolder",
													"type": "Expression"
												},
												"directory": {
													"value": "@concat(pipeline().parameters.DestinationFileDirectory,'/',item().name)",
													"type": "Expression"
												}
											}
										}
									]
								}
							]
						}
					}
				],
				"policy": {
					"elapsedTimeMetric": {},
					"cancelAfter": {}
				},
				"parameters": {
					"SourceFileFolder": {
						"type": "string",
						"defaultValue": "/"
					},
					"SourceFileDirectory": {
						"type": "string",
						"defaultValue": "/"
					},
					"DestinationFileFolder": {
						"type": "string",
						"defaultValue": "/"
					},
					"DestinationFileDirectory": {
						"type": "string",
						"defaultValue": "/"
					}
				},
				"annotations": []
			},
			"dependsOn": [
				"[concat(variables('factoryId'), '/datasets/BinarySourceFileStore')]",
				"[concat(variables('factoryId'), '/datasets/BinarySinkFileStore')]"
			]
		},
		{
			"name": "[concat(parameters('factoryName'), '/DataMovementLab')]",
			"type": "Microsoft.DataFactory/factories/pipelines",
			"apiVersion": "2018-06-01",
			"properties": {
				"activities": [
					{
						"name": "Copy data1",
						"type": "Copy",
						"dependsOn": [],
						"policy": {
							"timeout": "7.00:00:00",
							"retry": 0,
							"retryIntervalInSeconds": 30,
							"secureOutput": false,
							"secureInput": false
						},
						"userProperties": [],
						"typeProperties": {
							"source": {
								"type": "AzureSqlSource",
								"queryTimeout": "02:00:00",
								"partitionOption": "None"
							},
							"sink": {
								"type": "AzureSqlSink",
								"writeBehavior": "insert",
								"sqlWriterUseTableLock": false
							},
							"enableStaging": false,
							"translator": {
								"type": "TabularTranslator",
								"mappings": [
									{
										"source": {
											"name": "PersonId",
											"type": "Int32",
											"physicalType": "int"
										},
										"sink": {
											"name": "ManagerId",
											"type": "Int32",
											"physicalType": "int"
										}
									},
									{
										"source": {
											"name": "FirstName",
											"type": "String",
											"physicalType": "nvarchar"
										},
										"sink": {
											"name": "FirstName",
											"type": "String",
											"physicalType": "nvarchar"
										}
									},
									{
										"source": {
											"name": "LastName",
											"type": "String",
											"physicalType": "nvarchar"
										},
										"sink": {
											"name": "LastName",
											"type": "String",
											"physicalType": "nvarchar"
										}
									}
								],
								"typeConversion": true,
								"typeConversionSettings": {
									"allowDataTruncation": true,
									"treatBooleanAsNumber": false
								}
							}
						},
						"inputs": [
							{
								"referenceName": "AzureSqlPeople",
								"type": "DatasetReference",
								"parameters": {}
							}
						],
						"outputs": [
							{
								"referenceName": "AzureSqlOutput1",
								"type": "DatasetReference",
								"parameters": {}
							}
						]
					}
				],
				"policy": {
					"elapsedTimeMetric": {},
					"cancelAfter": {}
				},
				"annotations": []
			},
			"dependsOn": [
				"[concat(variables('factoryId'), '/datasets/AzureSqlPeople')]",
				"[concat(variables('factoryId'), '/datasets/AzureSqlOutput1')]"
			]
		},
		{
			"name": "[concat(parameters('factoryName'), '/ParametersLab')]",
			"type": "Microsoft.DataFactory/factories/pipelines",
			"apiVersion": "2018-06-01",
			"properties": {
				"activities": [
					{
						"name": "Get Metadata1",
						"type": "GetMetadata",
						"dependsOn": [],
						"policy": {
							"timeout": "7.00:00:00",
							"retry": 0,
							"retryIntervalInSeconds": 30,
							"secureOutput": false,
							"secureInput": false
						},
						"userProperties": [],
						"typeProperties": {
							"dataset": {
								"referenceName": "People1",
								"type": "DatasetReference",
								"parameters": {}
							},
							"fieldList": [
								"itemName",
								"lastModified",
								"size"
							],
							"storeSettings": {
								"type": "AzureBlobStorageReadSettings",
								"recursive": true,
								"enablePartitionDiscovery": false
							},
							"formatSettings": {
								"type": "DelimitedTextReadSettings"
							}
						}
					},
					{
						"name": "Set variable1",
						"type": "SetVariable",
						"dependsOn": [
							{
								"activity": "Get Metadata1",
								"dependencyConditions": [
									"Succeeded"
								]
							}
						],
						"userProperties": [],
						"typeProperties": {
							"variableName": "test",
							"value": {
								"value": "@activity('Get Metadata1').output.lastModified",
								"type": "Expression"
							}
						}
					},
					{
						"name": "Copy data1",
						"type": "Copy",
						"dependsOn": [],
						"policy": {
							"timeout": "7.00:00:00",
							"retry": 0,
							"retryIntervalInSeconds": 30,
							"secureOutput": false,
							"secureInput": false
						},
						"userProperties": [],
						"typeProperties": {
							"source": {
								"type": "BinarySource",
								"storeSettings": {
									"type": "AzureBlobStorageReadSettings",
									"recursive": true,
									"wildcardFileName": "*.csv",
									"deleteFilesAfterCompletion": false
								},
								"formatSettings": {
									"type": "BinaryReadSettings"
								}
							},
							"sink": {
								"type": "BinarySink",
								"storeSettings": {
									"type": "AzureBlobStorageWriteSettings"
								}
							},
							"enableStaging": false
						},
						"inputs": [
							{
								"referenceName": "AllCSVInput",
								"type": "DatasetReference",
								"parameters": {}
							}
						],
						"outputs": [
							{
								"referenceName": "OutputBinary1",
								"type": "DatasetReference",
								"parameters": {
									"FileName": {
										"value": "@(pipeline().TriggerTime).zip",
										"type": "Expression"
									}
								}
							}
						]
					}
				],
				"policy": {
					"elapsedTimeMetric": {},
					"cancelAfter": {}
				},
				"variables": {
					"test": {
						"type": "String"
					}
				},
				"annotations": []
			},
			"dependsOn": [
				"[concat(variables('factoryId'), '/datasets/People1')]",
				"[concat(variables('factoryId'), '/datasets/AllCSVInput')]",
				"[concat(variables('factoryId'), '/datasets/OutputBinary1')]"
			]
		},
		{
			"name": "[concat(parameters('factoryName'), '/TriggerWebCopy')]",
			"type": "Microsoft.DataFactory/factories/pipelines",
			"apiVersion": "2018-06-01",
			"properties": {
				"activities": [
					{
						"name": "Copy1",
						"type": "Copy",
						"dependsOn": [],
						"policy": {
							"timeout": "7.00:00:00",
							"retry": 2,
							"retryIntervalInSeconds": 30,
							"secureOutput": false,
							"secureInput": false
						},
						"userProperties": [],
						"typeProperties": {
							"source": {
								"type": "DelimitedTextSource",
								"storeSettings": {
									"type": "AzureBlobStorageReadSettings",
									"recursive": true,
									"enablePartitionDiscovery": false
								},
								"formatSettings": {
									"type": "DelimitedTextReadSettings"
								}
							},
							"sink": {
								"type": "DelimitedTextSink",
								"storeSettings": {
									"type": "AzureBlobStorageWriteSettings"
								},
								"formatSettings": {
									"type": "DelimitedTextWriteSettings",
									"quoteAllText": true,
									"fileExtension": ".txt"
								}
							},
							"enableStaging": false,
							"translator": {
								"type": "TabularTranslator",
								"typeConversion": true,
								"typeConversionSettings": {
									"allowDataTruncation": true,
									"treatBooleanAsNumber": false
								}
							}
						},
						"inputs": [
							{
								"referenceName": "People1",
								"type": "DatasetReference",
								"parameters": {}
							}
						],
						"outputs": [
							{
								"referenceName": "SinkWithParams",
								"type": "DatasetReference",
								"parameters": {}
							}
						]
					},
					{
						"name": "SendSuccessEmail",
						"type": "WebActivity",
						"dependsOn": [
							{
								"activity": "Copy1",
								"dependencyConditions": [
									"Succeeded"
								]
							}
						],
						"policy": {
							"timeout": "7.00:00:00",
							"retry": 0,
							"retryIntervalInSeconds": 30,
							"secureOutput": false,
							"secureInput": false
						},
						"userProperties": [],
						"typeProperties": {
							"url": "https://prod-58.eastus.logic.azure.com:443/workflows/f7319feb210c48f180521ede757a3421/triggers/manual/paths/invoke?api-version=2016-10-01&sp=%2Ftriggers%2Fmanual%2Frun&sv=1.0&sig=EswzZInwOw1xiJ2C9StnehkkyRJQ3K_Dp4Gn9OjADe4",
							"method": "POST",
							"headers": {
								"Content-Type": "application/json"
							},
							"body": {
								"message": "@{activity('Copy1').output.dataWritten}",
								"dataFactoryName": "@{pipeline().DataFactory}",
								"pipelineName": "@{pipeline().Pipeline}",
								"receiver": "@pipeline().parameters.receiver"
							}
						}
					},
					{
						"name": "SendFailEmail",
						"type": "WebActivity",
						"dependsOn": [
							{
								"activity": "Copy1",
								"dependencyConditions": [
									"Failed"
								]
							}
						],
						"policy": {
							"timeout": "7.00:00:00",
							"retry": 0,
							"retryIntervalInSeconds": 30,
							"secureOutput": false,
							"secureInput": false
						},
						"userProperties": [],
						"typeProperties": {
							"url": "https://prod-10.centralus.logic.azure.com:443/workflows/d6b5281763b74ccba0ea7dba26001785/triggers/manual/paths/invoke?api-version=2016-10-01&sp=%2Ftriggers%2Fmanual%2Frun&sv=1.0&sig=ucPpu7JfglHNeqI7gDPbd5eA-QfQm30n_RI-otnmVsM",
							"method": "POST",
							"headers": {
								"Content-Type": "application/json"
							},
							"body": {
								"message": "@{activity('Copy1').error.message}",
								"dataFactoryName": "@{pipeline().DataFactory}",
								"pipelineName": "@{pipeline().Pipeline}",
								"receiver": "@pipeline().parameters.receiver"
							}
						}
					}
				],
				"policy": {
					"elapsedTimeMetric": {},
					"cancelAfter": {}
				},
				"parameters": {
					"sourceContainer": {
						"type": "string"
					},
					"sinkContainer": {
						"type": "string"
					},
					"receiver": {
						"type": "string"
					}
				},
				"annotations": []
			},
			"dependsOn": [
				"[concat(variables('factoryId'), '/datasets/People1')]",
				"[concat(variables('factoryId'), '/datasets/SinkWithParams')]"
			]
		},
		{
			"name": "[concat(parameters('factoryName'), '/TriggersLab')]",
			"type": "Microsoft.DataFactory/factories/pipelines",
			"apiVersion": "2018-06-01",
			"properties": {
				"activities": [
					{
						"name": "Set variable1",
						"type": "SetVariable",
						"dependsOn": [],
						"userProperties": [],
						"typeProperties": {
							"variableName": "var1",
							"value": {
								"value": "@pipeline().parameters.param1",
								"type": "Expression"
							}
						}
					}
				],
				"policy": {
					"elapsedTimeMetric": {},
					"cancelAfter": {}
				},
				"parameters": {
					"param1": {
						"type": "string"
					}
				},
				"variables": {
					"var1": {
						"type": "String"
					}
				},
				"annotations": []
			},
			"dependsOn": []
		},
		{
			"name": "[concat(parameters('factoryName'), '/AllCSVInput')]",
			"type": "Microsoft.DataFactory/factories/datasets",
			"apiVersion": "2018-06-01",
			"properties": {
				"linkedServiceName": {
					"referenceName": "AzureBlobStorage1",
					"type": "LinkedServiceReference"
				},
				"annotations": [],
				"type": "Binary",
				"typeProperties": {
					"location": {
						"type": "AzureBlobStorageLocation",
						"fileName": "*.csv",
						"container": "blobcontainer1"
					}
				}
			},
			"dependsOn": [
				"[concat(variables('factoryId'), '/linkedServices/AzureBlobStorage1')]"
			]
		},
		{
			"name": "[concat(parameters('factoryName'), '/AzureSqlOutput1')]",
			"type": "Microsoft.DataFactory/factories/datasets",
			"apiVersion": "2018-06-01",
			"properties": {
				"linkedServiceName": {
					"referenceName": "AzureSqlDatabase1",
					"type": "LinkedServiceReference"
				},
				"annotations": [],
				"type": "AzureSqlTable",
				"schema": [
					{
						"name": "CustomerID",
						"type": "int",
						"precision": 10
					},
					{
						"name": "NameStyle",
						"type": "bit"
					},
					{
						"name": "Title",
						"type": "nvarchar"
					},
					{
						"name": "FirstName",
						"type": "nvarchar"
					},
					{
						"name": "MiddleName",
						"type": "nvarchar"
					},
					{
						"name": "LastName",
						"type": "nvarchar"
					},
					{
						"name": "Suffix",
						"type": "nvarchar"
					},
					{
						"name": "CompanyName",
						"type": "nvarchar"
					},
					{
						"name": "SalesPerson",
						"type": "nvarchar"
					},
					{
						"name": "EmailAddress",
						"type": "nvarchar"
					},
					{
						"name": "Phone",
						"type": "nvarchar"
					},
					{
						"name": "PasswordHash",
						"type": "varchar"
					},
					{
						"name": "PasswordSalt",
						"type": "varchar"
					},
					{
						"name": "rowguid",
						"type": "uniqueidentifier"
					},
					{
						"name": "ModifiedDate",
						"type": "datetime",
						"precision": 23,
						"scale": 3
					}
				],
				"typeProperties": {
					"schema": "dbo",
					"table": "Manager"
				}
			},
			"dependsOn": [
				"[concat(variables('factoryId'), '/linkedServices/AzureSqlDatabase1')]"
			]
		},
		{
			"name": "[concat(parameters('factoryName'), '/AzureSqlPeople')]",
			"type": "Microsoft.DataFactory/factories/datasets",
			"apiVersion": "2018-06-01",
			"properties": {
				"linkedServiceName": {
					"referenceName": "AzureSqlDatabase1",
					"type": "LinkedServiceReference"
				},
				"annotations": [],
				"type": "AzureSqlTable",
				"schema": [
					{
						"name": "PersonId",
						"type": "int",
						"precision": 10
					},
					{
						"name": "Age",
						"type": "int",
						"precision": 10
					},
					{
						"name": "FirstName",
						"type": "nvarchar"
					},
					{
						"name": "LastName",
						"type": "nvarchar"
					}
				],
				"typeProperties": {
					"schema": "dbo",
					"table": "Person"
				}
			},
			"dependsOn": [
				"[concat(variables('factoryId'), '/linkedServices/AzureSqlDatabase1')]"
			]
		},
		{
			"name": "[concat(parameters('factoryName'), '/BinarySinkFileStore')]",
			"type": "Microsoft.DataFactory/factories/datasets",
			"apiVersion": "2018-06-01",
			"properties": {
				"description": "Connection to your destination data store.",
				"linkedServiceName": {
					"referenceName": "AzureBlobStorage1",
					"type": "LinkedServiceReference"
				},
				"parameters": {
					"container": {
						"type": "string"
					},
					"directory": {
						"type": "string"
					}
				},
				"annotations": [],
				"type": "Binary",
				"typeProperties": {
					"location": {
						"type": "AzureBlobStorageLocation",
						"folderPath": {
							"value": "@dataset().directory",
							"type": "Expression"
						},
						"container": {
							"value": "@dataset().container",
							"type": "Expression"
						}
					}
				}
			},
			"dependsOn": [
				"[concat(variables('factoryId'), '/linkedServices/AzureBlobStorage1')]"
			]
		},
		{
			"name": "[concat(parameters('factoryName'), '/BinarySourceFileStore')]",
			"type": "Microsoft.DataFactory/factories/datasets",
			"apiVersion": "2018-06-01",
			"properties": {
				"description": "Connection to your source data store.",
				"linkedServiceName": {
					"referenceName": "AzureBlobStorage1",
					"type": "LinkedServiceReference"
				},
				"parameters": {
					"container": {
						"type": "string"
					},
					"directory": {
						"type": "string"
					}
				},
				"annotations": [],
				"type": "Binary",
				"typeProperties": {
					"location": {
						"type": "AzureBlobStorageLocation",
						"folderPath": {
							"value": "@dataset().directory",
							"type": "Expression"
						},
						"container": {
							"value": "@dataset().container",
							"type": "Expression"
						}
					}
				}
			},
			"dependsOn": [
				"[concat(variables('factoryId'), '/linkedServices/AzureBlobStorage1')]"
			]
		},
		{
			"name": "[concat(parameters('factoryName'), '/Json1')]",
			"type": "Microsoft.DataFactory/factories/datasets",
			"apiVersion": "2018-06-01",
			"properties": {
				"linkedServiceName": {
					"referenceName": "AzureBlobStorage1",
					"type": "LinkedServiceReference"
				},
				"annotations": [],
				"type": "Json",
				"typeProperties": {
					"location": {
						"type": "AzureBlobStorageLocation",
						"fileName": {
							"value": "@(pipeline().TriggerId).json",
							"type": "Expression"
						},
						"folderPath": "output",
						"container": "blobcontainer1"
					}
				},
				"schema": {}
			},
			"dependsOn": [
				"[concat(variables('factoryId'), '/linkedServices/AzureBlobStorage1')]"
			]
		},
		{
			"name": "[concat(parameters('factoryName'), '/Output1')]",
			"type": "Microsoft.DataFactory/factories/datasets",
			"apiVersion": "2018-06-01",
			"properties": {
				"linkedServiceName": {
					"referenceName": "AzureBlobStorage1",
					"type": "LinkedServiceReference"
				},
				"annotations": [],
				"type": "DelimitedText",
				"typeProperties": {
					"location": {
						"type": "AzureBlobStorageLocation",
						"fileName": "output.csv",
						"folderPath": "output",
						"container": "blobcontainer1"
					},
					"columnDelimiter": ",",
					"escapeChar": "\\",
					"firstRowAsHeader": true,
					"quoteChar": "\""
				},
				"schema": [
					{
						"name": "FirstName",
						"type": "String"
					},
					{
						"name": "LastName",
						"type": "String"
					},
					{
						"name": "Age",
						"type": "String"
					}
				]
			},
			"dependsOn": [
				"[concat(variables('factoryId'), '/linkedServices/AzureBlobStorage1')]"
			]
		},
		{
			"name": "[concat(parameters('factoryName'), '/OutputBinary1')]",
			"type": "Microsoft.DataFactory/factories/datasets",
			"apiVersion": "2018-06-01",
			"properties": {
				"linkedServiceName": {
					"referenceName": "AzureBlobStorage1",
					"type": "LinkedServiceReference"
				},
				"parameters": {
					"FileName": {
						"type": "string"
					}
				},
				"annotations": [],
				"type": "Binary",
				"typeProperties": {
					"location": {
						"type": "AzureBlobStorageLocation",
						"fileName": {
							"value": "@dataset().FileName",
							"type": "Expression"
						},
						"folderPath": "output",
						"container": "blobcontainer1"
					},
					"compression": {
						"type": "ZipDeflate",
						"level": "Fastest"
					}
				}
			},
			"dependsOn": [
				"[concat(variables('factoryId'), '/linkedServices/AzureBlobStorage1')]"
			]
		},
		{
			"name": "[concat(parameters('factoryName'), '/People1')]",
			"type": "Microsoft.DataFactory/factories/datasets",
			"apiVersion": "2018-06-01",
			"properties": {
				"linkedServiceName": {
					"referenceName": "AzureBlobStorage1",
					"type": "LinkedServiceReference"
				},
				"annotations": [],
				"type": "DelimitedText",
				"typeProperties": {
					"location": {
						"type": "AzureBlobStorageLocation",
						"fileName": "people.csv",
						"container": "blobcontainer1"
					},
					"columnDelimiter": ",",
					"escapeChar": "\\",
					"firstRowAsHeader": true,
					"quoteChar": "\""
				},
				"schema": [
					{
						"name": "FirstName",
						"type": "String"
					},
					{
						"name": "LastName",
						"type": "String"
					},
					{
						"name": "Age",
						"type": "String"
					}
				]
			},
			"dependsOn": [
				"[concat(variables('factoryId'), '/linkedServices/AzureBlobStorage1')]"
			]
		},
		{
			"name": "[concat(parameters('factoryName'), '/SinkWithParams')]",
			"type": "Microsoft.DataFactory/factories/datasets",
			"apiVersion": "2018-06-01",
			"properties": {
				"linkedServiceName": {
					"referenceName": "AzureBlobStorage1",
					"type": "LinkedServiceReference"
				},
				"annotations": [],
				"type": "DelimitedText",
				"typeProperties": {
					"location": {
						"type": "AzureBlobStorageLocation",
						"fileName": {
							"value": "@concat(pipeline().RunId, '.txt')",
							"type": "Expression"
						},
						"container": {
							"value": "pipeline().parameters.sinkContainer",
							"type": "Expression"
						}
					},
					"columnDelimiter": ",",
					"escapeChar": "\\",
					"firstRowAsHeader": true,
					"quoteChar": "\""
				},
				"schema": [
					{
						"name": "FirstName",
						"type": "String"
					},
					{
						"name": "LastName",
						"type": "String"
					},
					{
						"name": "Age",
						"type": "String"
					}
				]
			},
			"dependsOn": [
				"[concat(variables('factoryId'), '/linkedServices/AzureBlobStorage1')]"
			]
		},
		{
			"name": "[concat(parameters('factoryName'), '/AzureBlobStorage1')]",
			"type": "Microsoft.DataFactory/factories/linkedServices",
			"apiVersion": "2018-06-01",
			"properties": {
				"annotations": [],
				"type": "AzureBlobStorage",
				"typeProperties": {
					"connectionString": "[parameters('AzureBlobStorage1_connectionString')]"
				}
			},
			"dependsOn": []
		},
		{
			"name": "[concat(parameters('factoryName'), '/AzureKeyVault1')]",
			"type": "Microsoft.DataFactory/factories/linkedServices",
			"apiVersion": "2018-06-01",
			"properties": {
				"annotations": [],
				"type": "AzureKeyVault",
				"typeProperties": {
					"baseUrl": "[parameters('AzureKeyVault1_properties_typeProperties_baseUrl')]"
				}
			},
			"dependsOn": []
		},
		{
			"name": "[concat(parameters('factoryName'), '/AzureSqlDatabase1')]",
			"type": "Microsoft.DataFactory/factories/linkedServices",
			"apiVersion": "2018-06-01",
			"properties": {
				"annotations": [],
				"type": "AzureSqlDatabase",
				"typeProperties": {
					"connectionString": "[parameters('AzureSqlDatabase1_connectionString')]"
				}
			},
			"dependsOn": []
		},
		{
			"name": "[concat(parameters('factoryName'), '/TumblingWindow1')]",
			"type": "Microsoft.DataFactory/factories/triggers",
			"apiVersion": "2018-06-01",
			"properties": {
				"annotations": [],
				"runtimeState": "Started",
				"pipeline": {
					"pipelineReference": {
						"referenceName": "TriggersLab",
						"type": "PipelineReference"
					},
					"parameters": {
						"param1": "[parameters('TumblingWindow1_properties_pipeline_parameters_param1')]"
					}
				},
				"type": "TumblingWindowTrigger",
				"typeProperties": {
					"frequency": "Minute",
					"interval": 5,
					"startTime": "2022-04-21T10:19:00Z",
					"endTime": "2022-04-21T10:25:08Z",
					"delay": "00:00:00",
					"maxConcurrency": 50,
					"retryPolicy": {
						"intervalInSeconds": 30
					},
					"dependsOn": []
				}
			},
			"dependsOn": [
				"[concat(variables('factoryId'), '/pipelines/TriggersLab')]"
			]
		},
		{
			"name": "[concat(parameters('factoryName'), '/Trading Dragons')]",
			"type": "Microsoft.DataFactory/factories/pipelines",
			"apiVersion": "2018-06-01",
			"properties": {
				"activities": [
					{
						"name": "Lookup1",
						"type": "Lookup",
						"dependsOn": [],
						"policy": {
							"timeout": "7.00:00:00",
							"retry": 0,
							"retryIntervalInSeconds": 30,
							"secureOutput": false,
							"secureInput": false
						},
						"userProperties": [],
						"typeProperties": {
							"source": {
								"type": "DelimitedTextSource",
								"storeSettings": {
									"type": "AzureBlobStorageReadSettings",
									"recursive": true,
									"enablePartitionDiscovery": false
								},
								"formatSettings": {
									"type": "DelimitedTextReadSettings"
								}
							},
							"dataset": {
								"referenceName": "DelimitedText1",
								"type": "DatasetReference",
								"parameters": {}
							}
						}
					}
				],
				"policy": {
					"elapsedTimeMetric": {},
					"cancelAfter": {}
				},
				"annotations": []
			},
			"dependsOn": [
				"[concat(variables('factoryId'), '/datasets/DelimitedText1')]"
			]
		},
		{
			"name": "[concat(parameters('factoryName'), '/SelfHostedIRDragons')]",
			"type": "Microsoft.DataFactory/factories/integrationRuntimes",
			"apiVersion": "2018-06-01",
			"properties": {
				"type": "SelfHosted",
				"typeProperties": {}
			},
			"dependsOn": []
		},
		{
			"name": "[concat(parameters('factoryName'), '/MySql1')]",
			"type": "Microsoft.DataFactory/factories/linkedServices",
			"apiVersion": "2018-06-01",
			"properties": {
				"annotations": [],
				"type": "MySql",
				"typeProperties": {
					"connectionString": "[parameters('MySql1_connectionString')]"
				},
				"connectVia": {
					"referenceName": "SelfHostedIRDragons",
					"type": "IntegrationRuntimeReference"
				}
			},
			"dependsOn": [
				"[concat(variables('factoryId'), '/integrationRuntimes/SelfHostedIRDragons')]"
			]
		},
		{
			"name": "[concat(parameters('factoryName'), '/MySqlUsers')]",
			"type": "Microsoft.DataFactory/factories/datasets",
			"apiVersion": "2018-06-01",
			"properties": {
				"linkedServiceName": {
					"referenceName": "MySql1",
					"type": "LinkedServiceReference"
				},
				"annotations": [],
				"type": "MySqlTable",
				"schema": [],
				"typeProperties": {
					"tableName": "`users`"
				}
			},
			"dependsOn": [
				"[concat(variables('factoryId'), '/linkedServices/MySql1')]"
			]
		},
		{
			"name": "[concat(parameters('factoryName'), '/DelimitedText1')]",
			"type": "Microsoft.DataFactory/factories/datasets",
			"apiVersion": "2018-06-01",
			"properties": {
				"linkedServiceName": {
					"referenceName": "AzureBlobStorage1",
					"type": "LinkedServiceReference"
				},
				"annotations": [],
				"type": "DelimitedText",
				"typeProperties": {
					"location": {
						"type": "AzureBlobStorageLocation",
						"fileName": "TradingAppList.csv",
						"container": "blobcontainer1"
					},
					"columnDelimiter": ",",
					"escapeChar": "\\",
					"firstRowAsHeader": true,
					"quoteChar": "\""
				},
				"schema": [
					{
						"name": "ID",
						"type": "String"
					},
					{
						"name": "ItemTitle",
						"type": "String"
					},
					{
						"name": "ItemDescription",
						"type": "String"
					},
					{
						"name": "ItemPrice",
						"type": "String"
					},
					{
						"name": "ItemCategory",
						"type": "String"
					},
					{
						"name": "ItemImage",
						"type": "String"
					},
					{
						"name": "ItemLocation",
						"type": "String"
					},
					{
						"name": "WillingToTrade",
						"type": "String"
					},
					{
						"name": "ItemOwner",
						"type": "String"
					}
				]
			},
			"dependsOn": [
				"[concat(variables('factoryId'), '/linkedServices/AzureBlobStorage1')]"
			]
		}
	]
}